mkdocs_entangled/__init__.py
mkdocs_entangled/config.py
mkdocs_entangled/on_page_markdown.py
mkdocs_entangled/plugin.py
mkdocs_entangled/py.typed
mkdocs_entangled_plugin-0.5.0.dist-info/METADATA
mkdocs_entangled_plugin-0.5.0.dist-info/WHEEL
mkdocs_entangled_plugin-0.5.0.dist-info/entry_points.txt
mkdocs_entangled_plugin-0.5.0.dist-info/licenses/LICENSE
mkdocs_entangled_plugin-0.5.0.dist-info/RECORD
