Metadata-Version: 2.4
Name: mkdocs-entangled-plugin
Version: 0.5.0
Summary: Plugin for MkDocs helping with rendering Entangled (entangled.github.io) projects.
Author-email: Johan Hidding <j.hidding@esciencecenter.nl>
License-Expression: Apache-2.0
License-File: LICENSE
Requires-Python: <4,>=3.12
Requires-Dist: entangled-cli<3,>=2.2
Requires-Dist: mawk<0.2,>=0.1.7
Requires-Dist: mkdocs<2,>=1.4.2
